ailinttest/__init__.py
ailinttest/ailinttest.py
ailinttest/ailinttest_options.py
ailinttest/prompts.py
ailinttest-1.0.0.dist-info/LICENSE
ailinttest-1.0.0.dist-info/METADATA
ailinttest-1.0.0.dist-info/WHEEL
ailinttest-1.0.0.dist-info/RECORD
