Metadata-Version: 2.1
Name: ailinttest
Version: 1.0.0
Summary: A Python testing library that uses Large Language Models to verify code properties through natural language assertions.
Home-page: https://github.com/kdunee/ailinttest
License: MIT
Keywords: testing,pytest,unittest,ai-testing,llm,code-verification,natural-language,test-automation,code-quality,language-models
Author: Kosma Dunikowski
Author-email: kosmadunikowski@gmail.com
Requires-Python: >=3.10,<4.0
Classifier: Intended Audience :: Developers
Classifier: License :: OSI Approved :: MIT License
Classifier: Programming Language :: Python :: 3
Classifier: Programming Language :: Python :: 3.10
Classifier: Programming Language :: Python :: 3.11
Classifier: Programming Language :: Python :: 3.12
Classifier: Programming Language :: Python :: 3.13
Classifier: Topic :: Software Development :: Quality Assurance
Classifier: Topic :: Software Development :: Testing
Requires-Dist: litellm (>=1.49.2,<2.0.0)
